{
  "parent": "auraddons:recipes/root",
  "rewards": {
    "recipes": [
      "auraddons:ancient_ladder"
    ]
  },
  "criteria": {
    "has_items": {
      "trigger": "minecraft:inventory_changed",
      "conditions": {
        "items": [
          {
            "item": "naturesaura:ancient_stick"
          }
        ]
      }
    },
    "has_the_recipe": {
      "trigger": "minecraft:recipe_unlocked",
      "conditions": {
        "recipe": "auraddons:ancient_ladder"
      }
    }
  },
  "requirements": [
    [
      "has_items", "has_the_recipe"
    ]
  ]
}
